grep2/__init__.py
grep2/grep2.py
grep2-0.0.1.dist-info/METADATA
grep2-0.0.1.dist-info/WHEEL
grep2-0.0.1.dist-info/top_level.txt
grep2-0.0.1.dist-info/RECORD
