Metadata-Version: 2.1
Name: grep2
Version: 0.0.1
Summary: Unix grep command for software 2.0
Author-email: Ramya Kottapalli <rskottap@gmail.com>
Project-URL: source, https://github.com/rskottap/grep2
Project-URL: download, https://pypi.org/project/grep2/#files
Requires-Dist: gpts
Provides-Extra: develop
Requires-Dist: build ; extra == 'develop'
Requires-Dist: pytest ; extra == 'develop'
